r2_engine/__init__.py
r2_engine/chatbot_builder/__init__.py
r2_engine/chatbot_builder/builders/__init__.py
r2_engine/chatbot_builder/builders/base_builder.py
r2_engine/chatbot_builder/builders/hybrid_builder.py
r2_engine/chatbot_builder/builders/ocr_builder.py
r2_engine/chatbot_builder/builders/sql_builder.py
r2_engine/chatbot_builder/builders/vdb_builder.py
r2_engine/chatbot_builder/strategies/__init__.py
r2_engine/chatbot_builder/strategies/adaptive_rag.py
r2_engine/chatbot_builder/strategies/agentic_rag.py
r2_engine/chatbot_builder/strategies/base_strategy.py
r2_engine/chatbot_builder/strategies/corrective_rag.py
r2_engine/chatbot_builder/strategies/self_rag.py
r2_engine/chatbot_builder/tools/__init__.py
r2_engine/chatbot_builder/tools/search_web.py
r2_engine/data_input/__init__.py
r2_engine/data_input/data_ingestor.py
r2_engine/data_processing/__init__.py
r2_engine/data_processing/structured/__init__.py
r2_engine/data_processing/structured/converter.py
r2_engine/data_processing/structured/schema.py
r2_engine/data_processing/structured/utils.py
r2_engine/data_processing/unstructured/__init__.py
r2_engine/evals/__init__.py
r2_engine/evals/auto_improver.py
r2_engine/evals/evaluator_base.py
r2_engine/evals/evaluator_factory.py
r2_engine/evals/strategies/__init__.py
r2_engine/evals/strategies/answer_evaluator.py
r2_engine/evals/strategies/answer_hallucination_evaluator.py
r2_engine/evals/strategies/automatic_evaluator.py
r2_engine/evals/strategies/base_strategy.py
r2_engine/evals/strategies/docs_relevance_evaluator.py
r2_engine/evals/strategies/manual_evaluator.py
r2_engine/interfaces/__init__.py
r2_engine/interfaces/data_ingestor.py
r2_engine/user_input/__init__.py
r2_engine/user_input/user_input_handler.py
r2_engine/utils/__init__.py
r2_engine/utils/data_loader.py
r2_engine/utils/markdown_to_whatsapp_message.py
r2_engine/utils/whatsapp_service.py
r2_engine-0.0.78.dist-info/METADATA
r2_engine-0.0.78.dist-info/WHEEL
r2_engine-0.0.78.dist-info/top_level.txt
r2_engine-0.0.78.dist-info/RECORD
