Metadata-Version: 2.1
Name: r2_engine
Version: 0.0.78
Summary: Módulo para construir chatbots inteligentes para MTS Club
Home-page: https://github.com/CryptoDepto-CD/r2_engine
Author: Darvis Paz
Author-email: dpaz@ieee.org
License: MIT
Classifier: Programming Language :: Python :: 3
Classifier: Operating System :: OS Independent
Requires-Python: >=3.10
Requires-Dist: aiohappyeyeballs<3.0.0,>=2.4.0
Requires-Dist: aiohttp<4.0.0,>=3.10.5
Requires-Dist: aiosignal<2.0.0,>=1.3.1
Requires-Dist: annotated-types<1.0.0,>=0.7.0
Requires-Dist: anyio<5.0.0,>=4.6.0
Requires-Dist: asgiref<4.0.0,>=3.8.1
Requires-Dist: attrs<25.0.0,>=24.2.0
Requires-Dist: bcrypt<5.0.0,>=4.2.0
Requires-Dist: beautifulsoup4<5.0.0,>=4.12.3
Requires-Dist: blinker<2.0.0,>=1.8.2
Requires-Dist: build<2.0.0,>=1.2.2
Requires-Dist: cachetools<6.0.0,>=5.5.0
Requires-Dist: onnx<2.0.0,>=1.17.0
Requires-Dist: onnxruntime<2.0.0,>=1.19.2
Requires-Dist: certifi<2025.0.0,>=2024.8.30
Requires-Dist: cffi<2.0.0,>=1.17.1
Requires-Dist: chardet<6.0.0,>=5.2.0
Requires-Dist: charset-normalizer<4.0.0,>=3.3.2
Requires-Dist: chroma-hnswlib<0.8.0,>=0.7.6
Requires-Dist: click<9.0.0,>=8.1.7
Requires-Dist: clickhouse-connect<0.9.0,>=0.8.2
Requires-Dist: colorama<0.5.0,>=0.4.6
Requires-Dist: coloredlogs<16.0.0,>=15.0.1
Requires-Dist: cryptography<44.0.0,>=43.0.1
Requires-Dist: dataclasses-json<0.7.0,>=0.6.7
Requires-Dist: datasets<4.0.0,>=3.0.1
Requires-Dist: deepdiff<9.0.0,>=8.0.1
Requires-Dist: Deprecated<2.0.0,>=1.2.14
Requires-Dist: dill<0.4.0,>=0.3.8
Requires-Dist: distro<2.0.0,>=1.9.0
Requires-Dist: durationpy<1.0,>=0.7
Requires-Dist: einops<0.9.0,>=0.8.0
Requires-Dist: elastic-transport<9.0.0,>=8.15.0
Requires-Dist: elasticsearch<9.0.0,>=8.15.1
Requires-Dist: elasticsearch-serverless<0.5.0,>=0.4.0.20231031
Requires-Dist: emoji<3.0.0,>=2.13.2
Requires-Dist: et-xmlfile<2.0.0,>=1.1.0
Requires-Dist: faiss-cpu<2.0.0,>=1.8.0.post1
Requires-Dist: fastapi<1.0.0,>=0.115.0
Requires-Dist: fastembed<0.5.0,>=0.4.1
Requires-Dist: filelock<4.0.0,>=3.16.1
Requires-Dist: filetype<2.0.0,>=1.2.0
Requires-Dist: Flask<4.0.0,>=3.0.3
Requires-Dist: flatbuffers<25.0.0,>=24.3.25
Requires-Dist: frozenlist<2.0.0,>=1.4.1
Requires-Dist: fsspec<2025.0.0,>=2024.6.1
Requires-Dist: google-api-core<3.0.0,>=2.20.0
Requires-Dist: google-api-python-client<3.0.0,>=2.146.0
Requires-Dist: google-auth<3.0.0,>=2.35.0
Requires-Dist: google-auth-httplib2<1.0.0,>=0.2.0
Requires-Dist: google-auth-oauthlib<2.0.0,>=1.2.1
Requires-Dist: google-cloud-core<3.0.0,>=2.4.1
Requires-Dist: google-cloud-discoveryengine<1.0.0,>=0.12.2
Requires-Dist: googleapis-common-protos<2.0.0,>=1.65.0
Requires-Dist: greenlet<4.0.0,>=3.0.3
Requires-Dist: grpcio<2.0.0,>=1.66.2
Requires-Dist: grpcio-status<2.0.0,>=1.66.1
Requires-Dist: grpcio-tools<2.0.0,>=1.66.2
Requires-Dist: gspread<7.0.0,>=6.1.2
Requires-Dist: h11<1.0.0,>=0.14.0
Requires-Dist: h2<5.0.0,>=4.1.0
Requires-Dist: hpack<5.0.0,>=4.0.0
Requires-Dist: httpcore<2.0.0,>=1.0.5
Requires-Dist: httplib2<1.0.0,>=0.22.0
Requires-Dist: httptools<1.0.0,>=0.6.1
Requires-Dist: httpx<1.0.0,>=0.27.2
Requires-Dist: huggingface-hub<1.0.0,>=0.25.1
Requires-Dist: humanfriendly<11.0,>=10.0
Requires-Dist: hyperframe<7.0.0,>=6.0.1
Requires-Dist: idna<4.0.0,>=3.10
Requires-Dist: importlib-metadata<9.0.0,>=8.4.0
Requires-Dist: importlib-resources<7.0.0,>=6.4.5
Requires-Dist: iniconfig<3.0.0,>=2.0.0
Requires-Dist: itsdangerous<3.0.0,>=2.2.0
Requires-Dist: Jinja2<4.0.0,>=3.1.4
Requires-Dist: jiter<0.6.0,>=0.5.0
Requires-Dist: joblib<2.0.0,>=1.4.2
Requires-Dist: jq<2.0.0,>=1.8.0
Requires-Dist: jsonpatch<2.0.0,>=1.33
Requires-Dist: jsonpath-python<2.0.0,>=1.0.6
Requires-Dist: jsonpointer<4.0.0,>=3.0.0
Requires-Dist: kubernetes<32.0.0,>=31.0.0
Requires-Dist: langchain<0.4.0,>=0.3.4
Requires-Dist: langchain-chroma<0.2.0,>=0.1.4
Requires-Dist: langchain-community<0.4.0,>=0.3.3
Requires-Dist: langchain-core<0.4.0,>=0.3.12
Requires-Dist: langchain-elasticsearch<0.4.0,>=0.3.0
Requires-Dist: langchain-experimental<0.4.0,>=0.3.2
Requires-Dist: langchain-google-community<3.0.0,>=2.0.0
Requires-Dist: langchain-googledrive<0.3.0,>=0.2.28
Requires-Dist: langchain-huggingface<0.2.0,>=0.1.0
Requires-Dist: langchain-nvidia-ai-endpoints<0.4.0,>=0.3.0
Requires-Dist: langchain-openai<0.3.0,>=0.2.0
Requires-Dist: langchain-qdrant<0.2.0,>=0.1.4
Requires-Dist: langchain-text-splitters<0.4.0,>=0.3.0
Requires-Dist: langchain-unstructured<0.2.0,>=0.1.5
Requires-Dist: langchainhub<0.2.0,>=0.1.21
Requires-Dist: langdetect<2.0.0,>=1.0.9
Requires-Dist: langgraph<0.3.0,>=0.2.38
Requires-Dist: langgraph-checkpoint<3.0.0,>=2.0.0
Requires-Dist: langsmith<0.2.0,>=0.1.125
Requires-Dist: lark<2.0.0,>=1.2.2
Requires-Dist: loguru<0.8.0,>=0.7.2
Requires-Dist: lxml<6.0.0,>=5.3.0
Requires-Dist: lz4<5.0.0,>=4.3.3
Requires-Dist: markdown-it-py<4.0.0,>=3.0.0
Requires-Dist: MarkupSafe<3.0.0,>=2.1.5
Requires-Dist: marshmallow<4.0.0,>=3.22.0
Requires-Dist: mdurl<0.2.0,>=0.1.2
Requires-Dist: mmh3<5.0.0,>=4.1.0
Requires-Dist: monotonic<2.0.0,>=1.6
Requires-Dist: mpmath<2.0.0,>=1.3.0
Requires-Dist: msgpack<2.0.0,>=1.1.0
Requires-Dist: multidict<7.0.0,>=6.1.0
Requires-Dist: multiprocess<1.0.0,>=0.70.16
Requires-Dist: mypy-extensions<2.0.0,>=1.0.0
Requires-Dist: nest-asyncio<2.0.0,>=1.6.0
Requires-Dist: networkx<4.0,>=3.3
Requires-Dist: nltk<4.0.0,>=3.9.1
Requires-Dist: numpy<2.0.0,>=1.26.4
Requires-Dist: oauth2client<5.0.0,>=4.1.3
Requires-Dist: oauthlib<4.0.0,>=3.2.2
Requires-Dist: olefile<1.0.0,>=0.47
Requires-Dist: openai<2.0.0,>=1.47.1
Requires-Dist: openpyxl<4.0.0,>=3.1.5
Requires-Dist: backoff<2.3.0,>=1.10.0
Requires-Dist: chromadb<0.6.0,>=0.5.7
Requires-Dist: orderly-set<5.3.0,>=5.2.2
Requires-Dist: orjson<4.0.0,>=3.10.7
Requires-Dist: overrides<8.0.0,>=7.7.0
Requires-Dist: packaging<25.0,>=24.1
Requires-Dist: pandas<3.0.0,>=2.2.3
Requires-Dist: pillow<11.0.0,>=10.4.0
Requires-Dist: pip-tools<8.0.0,>=7.4.1
Requires-Dist: pluggy<2.0.0,>=1.5.0
Requires-Dist: portalocker<3.0.0,>=2.10.1
Requires-Dist: posthog<4.0.0,>=3.6.6
Requires-Dist: proto-plus<2.0.0,>=1.24.0
Requires-Dist: protobuf<6.0.0,>=5.28.2
Requires-Dist: psutil<7.0.0,>=6.0.0
Requires-Dist: psycopg2<3.0.0,>=2.9.9
Requires-Dist: pyarrow<18.0.0,>=17.0.0
Requires-Dist: pyasn1<0.7.0,>=0.6.1
Requires-Dist: pyasn1-modules<0.5.0,>=0.4.1
Requires-Dist: pycparser<3.0.0,>=2.22
Requires-Dist: pydantic<3.0.0,>=2.9.2
Requires-Dist: pydantic-settings<3.0.0,>=2.5.2
Requires-Dist: pydantic-core<3.0.0,>=2.23.4
Requires-Dist: pyee<13.0.0,>=12.0.0
Requires-Dist: Pygments<3.0.0,>=2.18.0
Requires-Dist: pyparsing<4.0.0,>=3.1.4
Requires-Dist: pypdf<6.0.0,>=5.0.0
Requires-Dist: PyPDF2<4.0.0,>=3.0.1
Requires-Dist: PyPika<0.49.0,>=0.48.9
Requires-Dist: pyproject-hooks<2.0.0,>=1.1.0
Requires-Dist: pyreadline3<4.0.0,>=3.5.4
Requires-Dist: PyStemmer<2.3.0,>=2.2.0.1
Requires-Dist: pytest<9.0.0,>=8.3.3
Requires-Dist: python-dateutil<3.0.0,>=2.9.0.post0
Requires-Dist: python-dotenv<2.0.0,>=1.0.1
Requires-Dist: python-iso639<2025.0.0,>=2024.4.27
Requires-Dist: python-magic<0.5.0,>=0.4.27
Requires-Dist: python-oxmsg<0.1.0,>=0.0.1
Requires-Dist: pytz<2025.0,>=2024.2
Requires-Dist: PyYAML<7.0.0,>=6.0.2
Requires-Dist: qdrant-client<2.0.0,>=1.11.3
Requires-Dist: RapidFuzz<4.0.0,>=3.10.0
Requires-Dist: regex<2025.0.0,>=2024.9.11
Requires-Dist: requests<3.0.0,>=2.32.3
Requires-Dist: requests-oauthlib<3.0.0,>=2.0.0
Requires-Dist: requests-toolbelt<2.0.0,>=1.0.0
Requires-Dist: rich<14.0.0,>=13.9.2
Requires-Dist: rsa<5.0.0,>=4.9
Requires-Dist: safetensors<0.5.0,>=0.4.5
Requires-Dist: scikit-learn<2.0.0,>=1.5.2
Requires-Dist: scipy<2.0.0,>=1.14.1
Requires-Dist: sentence-transformers<4.0.0,>=3.1.1
Requires-Dist: setuptools<76.0.0,>=75.1.0
Requires-Dist: shellingham<2.0.0,>=1.5.4
Requires-Dist: simsimd<6.0.0,>=5.4.2
Requires-Dist: six<2.0.0,>=1.16.0
Requires-Dist: sniffio<2.0.0,>=1.3.1
Requires-Dist: snowballstemmer<3.0.0,>=2.2.0
Requires-Dist: soupsieve<3.0.0,>=2.6
Requires-Dist: SQLAlchemy<3.0.0,>=2.0.35
Requires-Dist: starlette<0.39.0,>=0.38.6
Requires-Dist: sympy<2.0.0,>=1.13.3
Requires-Dist: tabulate<1.0.0,>=0.9.0
Requires-Dist: tenacity<9.0.0,>=8.3.0
Requires-Dist: threadpoolctl<4.0.0,>=3.5.0
Requires-Dist: tiktoken<0.8.0,>=0.7.0
Requires-Dist: tokenizers<0.21.0,>=0.20.0
Requires-Dist: tqdm<5.0.0,>=4.66.5
Requires-Dist: typer<0.13.0,>=0.12.5
Requires-Dist: types-requests<2.33.0,>=2.32.0.20240914
Requires-Dist: typing-inspect<1.0.0,>=0.9.0
Requires-Dist: typing-extensions<5.0.0,>=4.12.2
Requires-Dist: tzdata<2025.0.0,>=2024.2
Requires-Dist: u<0.2.0,>=0.1
Requires-Dist: unstructured<0.16.0,>=0.15.13
Requires-Dist: unstructured-client<0.26.0,>=0.25.9
Requires-Dist: uritemplate<5.0.0,>=4.1.1
Requires-Dist: urllib3<3.0.0,>=2.2.3
Requires-Dist: uvicorn<1.0.0,>=0.30.6
Requires-Dist: watchfiles<1.0.0,>=0.24.0
Requires-Dist: websocket-client<2.0.0,>=1.8.0
Requires-Dist: websockets<14.0.0,>=13.1
Requires-Dist: Werkzeug<4.0.0,>=3.0.4
Requires-Dist: wheel<1.0.0,>=0.44.0
Requires-Dist: wrapt<2.0.0,>=1.16.0
Requires-Dist: xxhash<4.0.0,>=3.5.0
Requires-Dist: yarl<2.0.0,>=1.12.1
Requires-Dist: zipp<4.0.0,>=3.20.2
Requires-Dist: zstandard<0.24.0,>=0.23.0
